FixedWidth-1.2.dist-info/METADATA
FixedWidth-1.2.dist-info/RECORD
FixedWidth-1.2.dist-info/WHEEL
FixedWidth-1.2.dist-info/top_level.txt
fixedwidth/__init__.py
fixedwidth/fixedwidth.py
